resetty/__init__.py
resetty/app_settings.py
resetty/apps.py
resetty/auth_password_validators.py
resetty/http.py
resetty/middleware.py
resetty/models.py
resetty/reset_service.py
resetty/signals.py
resetty/migrations/0001_initial.py
resetty/migrations/0002_auto_20200613_2025.py
resetty/migrations/0003_auto_20200613_2033.py
resetty/migrations/__init__.py
tests/__init__.py
tests/reset_service_test.py
resetty-1.0.2.dist-info/METADATA
resetty-1.0.2.dist-info/WHEEL
resetty-1.0.2.dist-info/top_level.txt
resetty-1.0.2.dist-info/RECORD
